src/__init__.py
src/date_utils.py
src/exceptions.py
src/log.py
src/main.py
src/cli/__init__.py
src/cli/auth.py
src/cli/paraview.py
src/cli/utils.py
src/cli/version.py
src/client/__init__.py
src/client/auth.py
src/client/base.py
src/client/client_socket_proxy.py
src/client/cloud.py
src/client/version.py
src/development/__init__.py
src/development/client_socket.py
src/development/client_socket_proxy.py
src/development/client_socket_proxy_ssl.py
src/development/client_ssl.py
src/development/client_to_gcp.py
src/development/dev.py
src/development/server_asyncio.py
src/development/server_socket.py
src/development/server_socket_proxy.py
src/manager/__init__.py
src/manager/auth_config.py
src/manager/login.py
src/model/__init__.py
src/model/access_token.py
src/model/base.py
src/model/resource.py
src/model/user.py
src/model/version.py
flowfusic_cli-0.1.1.dist-info/LICENSE
flowfusic_cli-0.1.1.dist-info/METADATA
flowfusic_cli-0.1.1.dist-info/NOTICE.txt
flowfusic_cli-0.1.1.dist-info/WHEEL
flowfusic_cli-0.1.1.dist-info/entry_points.txt
flowfusic_cli-0.1.1.dist-info/top_level.txt
flowfusic_cli-0.1.1.dist-info/RECORD
