Metadata-Version: 2.1
Name: flowfusic-cli
Version: 0.1.1
Summary: Command line tool for Flowfusic
Home-page: https://github.com/flowfusic/flowfusic-cli
Author: Flowfusic sp. z o.o.
Author-email: support@flowfusic.com
License: UNKNOWN
Keywords: flowfusic
Platform: UNKNOWN
Requires-Dist: click (==7.1.2)
Requires-Dist: clint (==0.5.1)
Requires-Dist: halo (==0.0.31)
Requires-Dist: requests (==2.25.1)
Requires-Dist: requests-toolbelt (==0.9.1)
Requires-Dist: marshmallow (==3.0.0a1)
Requires-Dist: pytz (>=2016.10)
Requires-Dist: tabulate (==0.8.7)
Requires-Dist: pathlib2 (==2.3.5)
Requires-Dist: PyYAML
Requires-Dist: raven
Requires-Dist: scandir ; python_version < "3.5"
